.gitignore
.travis.yml
LICENSE.txt
MANIFEST.in
README.md
README.rst
setup.cfg
setup.py
demo_notebook/README.md
demo_notebook/demo.ipynb
demo_notebook/report.html
demo_notebook/demo_xml/demo.xml
docs/OverleafLink.rtf
docs/pychemkin.pdf
docs/pychemkin.tex
examples/gridoutput_T0_x0.csv
examples/gridoutput_T0_x1.csv
examples/gridoutput_T1_x0.csv
examples/gridoutput_T1_x1.csv
examples/gridoutput_T2_x0.csv
examples/gridoutput_T2_x1.csv
examples/modeldocexample.html
examples/modeldocfig1.png
examples/modeldocfig2.png
examples/modeldocfig3.png
examples/modeldocfig4.png
pychemkin/BackwardCoeffs.py
pychemkin/ChemSolver.py
pychemkin/ChemViz.py
pychemkin/InputParser.py
pychemkin/ReactionCoeffs.py
pychemkin/SQLParser.py
pychemkin/__init__.py
pychemkin/chemkin.py
pychemkin/simpleIO.py
pychemkin.egg-info/PKG-INFO
pychemkin.egg-info/SOURCES.txt
pychemkin.egg-info/dependency_links.txt
pychemkin.egg-info/requires.txt
pychemkin.egg-info/top_level.txt
pychemkin/data/template.html
pychemkin/data/thermo_all.sqlite
tests/test_BackwardCoeffs.py
tests/test_ChemSolver.py
tests/test_ChemViz.py
tests/test_InputParser.py
tests/test_ReactionCoeffs.py
tests/test_SQLParser.py
tests/test_chemkin.py
tests/test_simpleIO.py
tests/test_data/test.csv
tests/test_data/test.pkl
tests/test_xml/demo.xml
tests/test_xml/rxns.xml
tests/test_xml/rxns_Oregonator.xml
tests/test_xml/rxns_Oregonator2.xml
tests/test_xml/rxns_bad_coeff.xml
tests/test_xml/rxns_bad_not_implement.xml
tests/test_xml/rxns_bad_reactants.xml
tests/test_xml/rxns_dimensionerror.xml
tests/test_xml/rxns_doubleddata.xml
tests/test_xml/rxns_invalid_reversible.xml
tests/test_xml/rxns_missing_A.xml
tests/test_xml/rxns_missing_attribute.xml
tests/test_xml/rxns_missing_k.xml
tests/test_xml/rxns_missingcoeffdata.xml
tests/test_xml/rxns_missingspecies.xml
tests/test_xml/rxns_pseudononelementary.xml
tests/test_xml/rxns_reversible.xml
tests/test_xml/rxns_single.xml
tests/test_xml/rxns_singlereversible.xml
tests/test_xml/rxnset_long.xml
tests/test_xml/rxnset_mixedreversible_long.xml