Metadata-Version: 1.1
Name: pychemkin
Version: 1.1.8
Summary: Chemical Kinetics Library
Home-page: https://github.com/cs207group4/cs207-FinalProject
Author: CS207 Group4
Author-email: zzy8200@gmail.com
License: GNU General Public License v3 (GPLv3)
Keywords: chemical kinetics
Platform: UNKNOWN
Classifier: Development Status :: 3 - Alpha
Classifier: Intended Audience :: Science/Research
Classifier: Topic :: Scientific/Engineering :: Chemistry
Classifier: License :: OSI Approved :: GNU General Public License v3 (GPLv3)
Classifier: Programming Language :: Python :: 3.4
Classifier: Programming Language :: Python :: 3.5
Classifier: Programming Language :: Python :: 3.6
